Metadata-Version: 2.1
Name: httpobs
Version: 0.9.3
Summary: HTTP Observatory: a set of tests and tools to scan your website for basic web hygeine.
Home-page: https://github.com/mozilla/http-observatory
Author: April King
Author-email: april@mozilla.com
License: UNKNOWN
Platform: UNKNOWN
Classifier: Development Status :: 4 - Beta
Classifier: Environment :: Web Environment
Classifier: Framework :: Flask
Classifier: Intended Audience :: Developers
Classifier: Intended Audience :: System Administrators
Classifier: License :: OSI Approved :: Mozilla Public License 2.0 (MPL 2.0)
Classifier: Natural Language :: English
Classifier: Programming Language :: Python :: 3 :: Only
Classifier: Topic :: Internet :: WWW/HTTP :: HTTP Servers
Classifier: Topic :: Security
Classifier: Topic :: Software Development :: Quality Assurance
License-File: LICENSE
Requires-Dist: amqp (==2.3.2)
Requires-Dist: beautifulsoup4 (==4.6.3)
Requires-Dist: billiard (==3.5.0.4)
Requires-Dist: celery (==4.2.1)
Requires-Dist: click (==7.0)
Requires-Dist: coverage (==4.5.2)
Requires-Dist: flake8 (==3.6.0)
Requires-Dist: httpobs-cli (==1.0.2)
Requires-Dist: itsdangerous (==1.1.0)
Requires-Dist: kombu (==4.2.1)
Requires-Dist: MarkupSafe (==1.1.0)
Requires-Dist: mccabe (==0.6.1)
Requires-Dist: nose (==1.3.7)
Requires-Dist: pep8 (==1.7.1)
Requires-Dist: pycodestyle (==2.4.0)
Requires-Dist: pyflakes (==2.0.0)
Requires-Dist: pytz (==2018.7)
Requires-Dist: vine (==1.1.4)
Requires-Dist: Werkzeug (==0.14.1)
Requires-Dist: psycopg2 (<2.8,>=2.7)
Requires-Dist: redis (==2.10.6)
Requires-Dist: psutil (==5.9.0)
Requires-Dist: publicsuffixlist (==0.7.12)
Requires-Dist: requests (==2.27.1)
Requires-Dist: Flask (==1.0.2)
Requires-Dist: uWSGI (==2.0.17.1)
